Adafruit_VCNL40xx/VCNL40xx.py
Adafruit_VCNL40xx/__init__.py
Adafruit_VCNL40xx-1.0.2.dist-info/metadata.json
Adafruit_VCNL40xx-1.0.2.dist-info/METADATA
Adafruit_VCNL40xx-1.0.2.dist-info/RECORD
Adafruit_VCNL40xx-1.0.2.dist-info/WHEEL
Adafruit_VCNL40xx-1.0.2.dist-info/DESCRIPTION.rst
Adafruit_VCNL40xx-1.0.2.dist-info/dependency_links.txt
Adafruit_VCNL40xx-1.0.2.dist-info/top_level.txt
