Metadata-Version: 2.0
Name: Adafruit-VCNL40xx
Version: 1.0.2
Summary: Python code to use the VCNL4000 & VCNL4010 proximity sensors with the Raspberry Pi & BeagleBone Black.
Home-page: https://github.com/adafruit/Adafruit_Python_VCNL40xx/
Author: Tony DiCola
Author-email: tdicola@adafruit.com
License: MIT
Platform: UNKNOWN
Classifier: Development Status :: 4 - Beta
Classifier: Operating System :: POSIX :: Linux
Classifier: License :: OSI Approved :: MIT License
Classifier: Intended Audience :: Developers
Classifier: Programming Language :: Python :: 2.7
Classifier: Programming Language :: Python :: 3
Classifier: Topic :: Software Development
Classifier: Topic :: System :: Hardware
Requires-Dist: Adafruit-GPIO (>=0.6.5)
